hyperlpr/__init__.py
hyperlpr/hyperlpr.py
hyperlpr/table_chs.py
hyperlpr/models/cascade/char/char_single.xml
hyperlpr/models/cascade/detector/detector_ch.xml
hyperlpr/models/dnn/HorizonalFinemapping.caffemodel
hyperlpr/models/dnn/HorizonalFinemapping.prototxt
hyperlpr/models/dnn/SegmenationFree-Inception.caffemodel
hyperlpr/models/dnn/SegmenationFree-Inception.prototxt
hyperlpr/models/dnn/mininet_ssd_v1.caffemodel
hyperlpr/models/dnn/mininet_ssd_v1.prototxt
hyperlpr/models/dnn/refinenet.caffemodel
hyperlpr/models/dnn/refinenet.prototxt
hyperlpr-0.0.2.dist-info/METADATA
hyperlpr-0.0.2.dist-info/WHEEL
hyperlpr-0.0.2.dist-info/top_level.txt
hyperlpr-0.0.2.dist-info/RECORD
